chromatrace/RabbitMQ.py
chromatrace/__init__.py
chromatrace/django.py
chromatrace/fastapi.py
chromatrace/logging_config.py
chromatrace/logging_settings.py
chromatrace/socketio.py
chromatrace/tracer.py
chromatrace/uvicorn/__init__.py
chromatrace/uvicorn/config.py
chromatrace/uvicorn/formatters.py
chromatrace-0.2.13.dist-info/METADATA
chromatrace-0.2.13.dist-info/WHEEL
chromatrace-0.2.13.dist-info/licenses/LICENSE
chromatrace-0.2.13.dist-info/RECORD
