Metadata-Version: 2.4
Name: chromatrace
Version: 0.2.13
Summary: Advanced Python logging with tracing, coloring and FastAPI, Django, and SocketIO integrations
Project-URL: Homepage, https://github.com/Msameim181/Python-Logging-Best-Practice
Project-URL: Documentation, https://github.com/Msameim181/Python-Logging-Best-Practice#readme
Project-URL: Repository, https://github.com/Msameim181/Python-Logging-Best-Practice.git
Project-URL: Issues, https://github.com/Msameim181/Python-Logging-Best-Practice/issues
Author-email: Mohammad Mahdi Samei <9259samei@gmail.com>
License:                     GNU AFFERO GENERAL PUBLIC LICENSE
License-File: LICENSE
Classifier: Intended Audience :: Developers
Classifier: License :: OSI Approved :: GNU Affero General Public License v3
Classifier: Operating System :: OS Independent
Classifier: Programming Language :: Python :: 3.10
Classifier: Topic :: Software Development :: Libraries :: Python Modules
Classifier: Topic :: System :: Logging
Requires-Python: >=3.10
Requires-Dist: asyncio==3.4.3
Requires-Dist: fastapi==0.100.0
Requires-Dist: httpx==0.27.2
Requires-Dist: lagom==2.6.0
Requires-Dist: pydantic==2.9.2
Requires-Dist: python-multipart==0.0.10
Requires-Dist: python-socketio==5.12.1
Requires-Dist: python-socketio[client]==5.12.1
Requires-Dist: uvicorn-worker==0.2.0
Requires-Dist: uvicorn[standard]==0.30.6
